{
	"name": "Bunbun",
	"type": "ancestry",
	"img": "icons/creatures/mammals/rabbit-movement-glowing-green.webp",
	"system": {
		"macro": "",
		"identifier": "",
		"rules": [],
		"description": "<p>Bunbun are agile and unpredictable, using their powerful legs to leap great distances and catch foes off guard. Facing a Bunbun means contending with an opponent who can strike from unexpected angles and swiftly reposition themselves in the heat of battle.</p>",
		"exotic": true,
		"size": [
			"small"
		],
		"defaultBonus": "Compendium.nimble.nimble-ancestry-bonuses.Item.1cSW678NQBiWN5m4"
	},
	"effects": [],
	"folder": null,
	"flags": {},
	"_stats": {
		"coreVersion": "13.347",
		"systemId": "nimble",
		"systemVersion": "0.1.7",
		"createdTime": 1756448281398,
		"modifiedTime": 1756504596317,
		"lastModifiedBy": "zvcmZ9cAKxekqF5X"
	},
	"_id": "H1B0wnT9GKexRhyG"
}